{"name":"Registro de clientes","id":"compras-en-pagina-de-pruebas;registro-de-clientes","testSteps":[{"number":1,"description":"Dado que el usuario esta en la pagina de inicio","duration":12360,"startTime":"2023-03-22T13:52:07.667566300-05:00[America/Bogota]","screenshots":[{"screenshot":"17b5948d43781c40babcc012c063c5886b2a4a4a623c701541207c7c5fbc29e4.png","timeStamp":1679511140028}],"result":"SUCCESS","precondition":false,"level":0,"children":[{"number":2,"description":"Juanes abrir pagina inicial","duration":4795,"startTime":"2023-03-22T13:52:14.825538900-05:00[America/Bogota]","screenshots":[{"screenshot":"eafeaa3fb7da7e39c2f6290aacb5c03acde6480fb90e8e470f11dc51538fb87f.png","timeStamp":1679511135601},{"screenshot":"17b5948d43781c40babcc012c063c5886b2a4a4a623c701541207c7c5fbc29e4.png","timeStamp":1679511139621}],"result":"SUCCESS","precondition":false,"level":1,"children":[{"number":3,"description":"Juanes opens the Pagina inicial","duration":3941,"startTime":"2023-03-22T13:52:15.632503900-05:00[America/Bogota]","screenshots":[{"screenshot":"eafeaa3fb7da7e39c2f6290aacb5c03acde6480fb90e8e470f11dc51538fb87f.png","timeStamp":1679511135871},{"screenshot":"17b5948d43781c40babcc012c063c5886b2a4a4a623c701541207c7c5fbc29e4.png","timeStamp":1679511139574}],"result":"SUCCESS","precondition":false,"level":2}]}]},{"number":4,"description":"Cuando navega hasta la el formulario de registro","duration":1881,"startTime":"2023-03-22T13:52:20.028360300-05:00[America/Bogota]","screenshots":[{"screenshot":"c1829d8dca74925604d9e67d67758b4ce1c7d69b5b633fc5b4e68bddcc732cd6.png","timeStamp":1679511141909}],"result":"SUCCESS","precondition":false,"level":0,"children":[{"number":5,"description":"Juanes navegar al registro","duration":1813,"startTime":"2023-03-22T13:52:20.080801800-05:00[America/Bogota]","screenshots":[{"screenshot":"c1829d8dca74925604d9e67d67758b4ce1c7d69b5b633fc5b4e68bddcc732cd6.png","timeStamp":1679511141893}],"result":"SUCCESS","precondition":false,"level":1,"children":[{"number":6,"description":"Juanes clicks on Boton ir al registro","duration":1338,"startTime":"2023-03-22T13:52:20.534328300-05:00[America/Bogota]","screenshots":[{"screenshot":"c1829d8dca74925604d9e67d67758b4ce1c7d69b5b633fc5b4e68bddcc732cd6.png","timeStamp":1679511141873}],"result":"SUCCESS","precondition":false,"level":2}]}]},{"number":7,"description":"Y Llena todos los campos","duration":2313,"startTime":"2023-03-22T13:52:21.909615500-05:00[America/Bogota]","screenshots":[{"screenshot":"a0fc102f44e531c0a7cc82b91a20a2edaa6d965c18cfe5ef783912c217c1d974.png","timeStamp":1679511142123}],"exception":{"errorType":"org.openqa.selenium.NoSuchWindowException","message":"no such window: target window already closed\nfrom unknown error: web view not found\n  (Session info: chrome\u003d111.0.5563.65)\nBuild info: version: \u00273.141.59\u0027, revision: \u0027e82be7d358\u0027, time: \u00272018-11-14T08:17:03\u0027\nSystem info: host: \u0027LAPTOP-87LGHN0U\u0027, ip: \u0027192.168.0.5\u0027, os.name: \u0027Windows 11\u0027, os.arch: \u0027amd64\u0027, os.version: \u002710.0\u0027, java.version: \u002711.0.18\u0027\nDriver info: org.openqa.selenium.chrome.ChromeDriver\nCapabilities {acceptInsecureCerts: false, browserName: chrome, browserVersion: 111.0.5563.65, chrome: {chromedriverVersion: 111.0.5563.64 (c710e93d5b63..., userDataDir: C:\\Users\\ivan0\\AppData\\Loca...}, goog:chromeOptions: {debuggerAddress: localhost:55932}, javascriptEnabled: true, networkConnectionEnabled: false, pageLoadStrategy: normal, platform: WINDOWS, platformName: WINDOWS, proxy: Proxy(), setWindowRect: true, strictFileInteractability: false, timeouts: {implicit: 0, pageLoad: 300000, script: 30000}, unhandledPromptBehavior: ignore, webauthn:extension:credBlob: true, webauthn:extension:largeBlob: true, webauthn:extension:minPinLength: true, webauthn:extension:prf: true, webauthn:virtualAuthenticators: true}\nSession ID: 75a0a10f9f9f8880c527d66ca5a097ca","stackTrace":[{"classLoaderName":"app","declaringClass":"com.sofkau.tasks.Registrarse","methodName":"performAs","fileName":"Registrarse.java","lineNumber":44,"format":1},{"classLoaderName":"app","declaringClass":"com.sofkau.stepdefinitions.RegistroInicioSesionStepDefinitions","methodName":"llenaTodosLosCampos","fileName":"RegistroInicioSesionStepDefinitions.java","lineNumber":31,"format":1},{"classLoaderName":"app","declaringClass":"io.cucumber.java.Invoker","methodName":"invoke","fileName":"Invoker.java","lineNumber":27,"format":1},{"classLoaderName":"app","declaringClass":"io.cucumber.java.JavaStepDefinition","methodName":"execute","fileName":"JavaStepDefinition.java","lineNumber":27,"format":1},{"classLoaderName":"app","declaringClass":"io.cucumber.core.runner.PickleStepDefinitionMatch","methodName":"runStep","fileName":"PickleStepDefinitionMatch.java","lineNumber":63,"format":1},{"classLoaderName":"app","declaringClass":"io.cucumber.core.runner.TestStep","methodName":"executeStep","fileName":"TestStep.java","lineNumber":64,"format":1},{"classLoaderName":"app","declaringClass":"io.cucumber.core.runner.TestStep","methodName":"run","fileName":"TestStep.java","lineNumber":49,"format":1},{"classLoaderName":"app","declaringClass":"io.cucumber.core.runner.PickleStepTestStep","methodName":"run","fileName":"PickleStepTestStep.java","lineNumber":46,"format":1},{"classLoaderName":"app","declaringClass":"io.cucumber.core.runner.TestCase","methodName":"run","fileName":"TestCase.java","lineNumber":51,"format":1},{"classLoaderName":"app","declaringClass":"io.cucumber.core.runner.Runner","methodName":"runPickle","fileName":"Runner.java","lineNumber":67,"format":1},{"classLoaderName":"app","declaringClass":"io.cucumber.junit.FeatureRunner","methodName":"runChild","fileName":"FeatureRunner.java","lineNumber":83,"format":1},{"classLoaderName":"app","declaringClass":"io.cucumber.junit.FeatureRunner","methodName":"runChild","fileName":"FeatureRunner.java","lineNumber":24,"format":1},{"classLoaderName":"app","declaringClass":"io.cucumber.junit.CucumberSerenityRunner","methodName":"runChild","fileName":"CucumberSerenityRunner.java","lineNumber":227,"format":1},{"classLoaderName":"app","declaringClass":"io.cucumber.junit.CucumberSerenityRunner","methodName":"runChild","fileName":"CucumberSerenityRunner.java","lineNumber":54,"format":1},{"classLoaderName":"app","declaringClass":"worker.org.gradle.process.internal.worker.GradleWorkerMain","methodName":"run","fileName":"GradleWorkerMain.java","lineNumber":69,"format":1},{"classLoaderName":"app","declaringClass":"worker.org.gradle.process.internal.worker.GradleWorkerMain","methodName":"main","fileName":"GradleWorkerMain.java","lineNumber":74,"format":1}]},"result":"ERROR","precondition":false,"level":0,"children":[{"number":8,"description":"Juanes registrarse","duration":2052,"startTime":"2023-03-22T13:52:22.139214500-05:00[America/Bogota]","screenshots":[{"screenshot":"a0fc102f44e531c0a7cc82b91a20a2edaa6d965c18cfe5ef783912c217c1d974.png","timeStamp":1679511142170}],"exception":{"errorType":"org.openqa.selenium.NoSuchWindowException","message":"no such window: target window already closed\nfrom unknown error: web view not found\n  (Session info: chrome\u003d111.0.5563.65)\nBuild info: version: \u00273.141.59\u0027, revision: \u0027e82be7d358\u0027, time: \u00272018-11-14T08:17:03\u0027\nSystem info: host: \u0027LAPTOP-87LGHN0U\u0027, ip: \u0027192.168.0.5\u0027, os.name: \u0027Windows 11\u0027, os.arch: \u0027amd64\u0027, os.version: \u002710.0\u0027, java.version: \u002711.0.18\u0027\nDriver info: org.openqa.selenium.chrome.ChromeDriver\nCapabilities {acceptInsecureCerts: false, browserName: chrome, browserVersion: 111.0.5563.65, chrome: {chromedriverVersion: 111.0.5563.64 (c710e93d5b63..., userDataDir: C:\\Users\\ivan0\\AppData\\Loca...}, goog:chromeOptions: {debuggerAddress: localhost:55932}, javascriptEnabled: true, networkConnectionEnabled: false, pageLoadStrategy: normal, platform: WINDOWS, platformName: WINDOWS, proxy: Proxy(), setWindowRect: true, strictFileInteractability: false, timeouts: {implicit: 0, pageLoad: 300000, script: 30000}, unhandledPromptBehavior: ignore, webauthn:extension:credBlob: true, webauthn:extension:largeBlob: true, webauthn:extension:minPinLength: true, webauthn:extension:prf: true, webauthn:virtualAuthenticators: true}\nSession ID: 75a0a10f9f9f8880c527d66ca5a097ca","stackTrace":[{"classLoaderName":"app","declaringClass":"com.sofkau.tasks.Registrarse","methodName":"performAs","fileName":"Registrarse.java","lineNumber":44,"format":1},{"classLoaderName":"app","declaringClass":"com.sofkau.stepdefinitions.RegistroInicioSesionStepDefinitions","methodName":"llenaTodosLosCampos","fileName":"RegistroInicioSesionStepDefinitions.java","lineNumber":31,"format":1},{"classLoaderName":"app","declaringClass":"io.cucumber.java.Invoker","methodName":"invoke","fileName":"Invoker.java","lineNumber":27,"format":1},{"classLoaderName":"app","declaringClass":"io.cucumber.java.JavaStepDefinition","methodName":"execute","fileName":"JavaStepDefinition.java","lineNumber":27,"format":1},{"classLoaderName":"app","declaringClass":"io.cucumber.core.runner.PickleStepDefinitionMatch","methodName":"runStep","fileName":"PickleStepDefinitionMatch.java","lineNumber":63,"format":1},{"classLoaderName":"app","declaringClass":"io.cucumber.core.runner.TestStep","methodName":"executeStep","fileName":"TestStep.java","lineNumber":64,"format":1},{"classLoaderName":"app","declaringClass":"io.cucumber.core.runner.TestStep","methodName":"run","fileName":"TestStep.java","lineNumber":49,"format":1},{"classLoaderName":"app","declaringClass":"io.cucumber.core.runner.PickleStepTestStep","methodName":"run","fileName":"PickleStepTestStep.java","lineNumber":46,"format":1},{"classLoaderName":"app","declaringClass":"io.cucumber.core.runner.TestCase","methodName":"run","fileName":"TestCase.java","lineNumber":51,"format":1},{"classLoaderName":"app","declaringClass":"io.cucumber.core.runner.Runner","methodName":"runPickle","fileName":"Runner.java","lineNumber":67,"format":1},{"classLoaderName":"app","declaringClass":"io.cucumber.junit.FeatureRunner","methodName":"runChild","fileName":"FeatureRunner.java","lineNumber":83,"format":1},{"classLoaderName":"app","declaringClass":"io.cucumber.junit.FeatureRunner","methodName":"runChild","fileName":"FeatureRunner.java","lineNumber":24,"format":1},{"classLoaderName":"app","declaringClass":"io.cucumber.junit.CucumberSerenityRunner","methodName":"runChild","fileName":"CucumberSerenityRunner.java","lineNumber":227,"format":1},{"classLoaderName":"app","declaringClass":"io.cucumber.junit.CucumberSerenityRunner","methodName":"runChild","fileName":"CucumberSerenityRunner.java","lineNumber":54,"format":1},{"classLoaderName":"app","declaringClass":"worker.org.gradle.process.internal.worker.GradleWorkerMain","methodName":"run","fileName":"GradleWorkerMain.java","lineNumber":69,"format":1},{"classLoaderName":"app","declaringClass":"worker.org.gradle.process.internal.worker.GradleWorkerMain","methodName":"main","fileName":"GradleWorkerMain.java","lineNumber":74,"format":1}]},"result":"ERROR","precondition":false,"level":1,"children":[{"number":9,"description":"Juanes enters \u0027Ivan\u0027 into campo nombre","duration":1345,"startTime":"2023-03-22T13:52:22.233420900-05:00[America/Bogota]","screenshots":[{"screenshot":"a0fc102f44e531c0a7cc82b91a20a2edaa6d965c18cfe5ef783912c217c1d974.png","timeStamp":1679511142567},{"screenshot":"49f9f5b5b3e8dbecf9a25052bbd76ddcee001171d98d488cc44af3dc6eae78d4.png","timeStamp":1679511143579}],"result":"SUCCESS","precondition":false,"level":2},{"number":10,"description":"Juanes enters \u0027damir29305@etondy.com\u0027 into campo email","duration":583,"startTime":"2023-03-22T13:52:23.579312500-05:00[America/Bogota]","screenshots":[{"screenshot":"49f9f5b5b3e8dbecf9a25052bbd76ddcee001171d98d488cc44af3dc6eae78d4.png","timeStamp":1679511143596}],"exception":{"errorType":"org.openqa.selenium.NoSuchWindowException","message":"no such window: target window already closed\nfrom unknown error: web view not found\n  (Session info: chrome\u003d111.0.5563.65)\nBuild info: version: \u00273.141.59\u0027, revision: \u0027e82be7d358\u0027, time: \u00272018-11-14T08:17:03\u0027\nSystem info: host: \u0027LAPTOP-87LGHN0U\u0027, ip: \u0027192.168.0.5\u0027, os.name: \u0027Windows 11\u0027, os.arch: \u0027amd64\u0027, os.version: \u002710.0\u0027, java.version: \u002711.0.18\u0027\nDriver info: org.openqa.selenium.chrome.ChromeDriver\nCapabilities {acceptInsecureCerts: false, browserName: chrome, browserVersion: 111.0.5563.65, chrome: {chromedriverVersion: 111.0.5563.64 (c710e93d5b63..., userDataDir: C:\\Users\\ivan0\\AppData\\Loca...}, goog:chromeOptions: {debuggerAddress: localhost:55932}, javascriptEnabled: true, networkConnectionEnabled: false, pageLoadStrategy: normal, platform: WINDOWS, platformName: WINDOWS, proxy: Proxy(), setWindowRect: true, strictFileInteractability: false, timeouts: {implicit: 0, pageLoad: 300000, script: 30000}, unhandledPromptBehavior: ignore, webauthn:extension:credBlob: true, webauthn:extension:largeBlob: true, webauthn:extension:minPinLength: true, webauthn:extension:prf: true, webauthn:virtualAuthenticators: true}\nSession ID: 75a0a10f9f9f8880c527d66ca5a097ca","stackTrace":[{"classLoaderName":"app","declaringClass":"com.sofkau.tasks.Registrarse","methodName":"performAs","fileName":"Registrarse.java","lineNumber":44,"format":1},{"classLoaderName":"app","declaringClass":"com.sofkau.stepdefinitions.RegistroInicioSesionStepDefinitions","methodName":"llenaTodosLosCampos","fileName":"RegistroInicioSesionStepDefinitions.java","lineNumber":31,"format":1},{"classLoaderName":"app","declaringClass":"io.cucumber.java.Invoker","methodName":"invoke","fileName":"Invoker.java","lineNumber":27,"format":1},{"classLoaderName":"app","declaringClass":"io.cucumber.java.JavaStepDefinition","methodName":"execute","fileName":"JavaStepDefinition.java","lineNumber":27,"format":1},{"classLoaderName":"app","declaringClass":"io.cucumber.core.runner.PickleStepDefinitionMatch","methodName":"runStep","fileName":"PickleStepDefinitionMatch.java","lineNumber":63,"format":1},{"classLoaderName":"app","declaringClass":"io.cucumber.core.runner.TestStep","methodName":"executeStep","fileName":"TestStep.java","lineNumber":64,"format":1},{"classLoaderName":"app","declaringClass":"io.cucumber.core.runner.TestStep","methodName":"run","fileName":"TestStep.java","lineNumber":49,"format":1},{"classLoaderName":"app","declaringClass":"io.cucumber.core.runner.PickleStepTestStep","methodName":"run","fileName":"PickleStepTestStep.java","lineNumber":46,"format":1},{"classLoaderName":"app","declaringClass":"io.cucumber.core.runner.TestCase","methodName":"run","fileName":"TestCase.java","lineNumber":51,"format":1},{"classLoaderName":"app","declaringClass":"io.cucumber.core.runner.Runner","methodName":"runPickle","fileName":"Runner.java","lineNumber":67,"format":1},{"classLoaderName":"app","declaringClass":"io.cucumber.junit.FeatureRunner","methodName":"runChild","fileName":"FeatureRunner.java","lineNumber":83,"format":1},{"classLoaderName":"app","declaringClass":"io.cucumber.junit.FeatureRunner","methodName":"runChild","fileName":"FeatureRunner.java","lineNumber":24,"format":1},{"classLoaderName":"app","declaringClass":"io.cucumber.junit.CucumberSerenityRunner","methodName":"runChild","fileName":"CucumberSerenityRunner.java","lineNumber":227,"format":1},{"classLoaderName":"app","declaringClass":"io.cucumber.junit.CucumberSerenityRunner","methodName":"runChild","fileName":"CucumberSerenityRunner.java","lineNumber":54,"format":1},{"classLoaderName":"app","declaringClass":"worker.org.gradle.process.internal.worker.GradleWorkerMain","methodName":"run","fileName":"GradleWorkerMain.java","lineNumber":69,"format":1},{"classLoaderName":"app","declaringClass":"worker.org.gradle.process.internal.worker.GradleWorkerMain","methodName":"main","fileName":"GradleWorkerMain.java","lineNumber":74,"format":1}]},"result":"ERROR","precondition":false,"level":2}]}]},{"number":11,"description":"Entonces el usuario debe ser redireccionado a la pagina principal","duration":46,"startTime":"2023-03-22T13:52:24.270365600-05:00[America/Bogota]","result":"SKIPPED","precondition":false,"level":0}],"userStory":{"id":"compras-en-pagina-de-pruebas","storyName":"Compras en pagina de pruebas","path":"file:///C:/Users/ivan0/Downloads/Screenplay/C1-2023-QA-Auto-DemoScreenPlay/ScreenPlay/src/test/resources/features/comprar.feature","narrative":"  yo como usuario de la pagina automation exercise\n  quiero crear una cuenta e ingresar\n  para poder comprar productos en la página","type":"feature"},"featureTag":{"name":"Features/Compras en pagina de pruebas","type":"feature","displayName":"Features/Compras en pagina de pruebas"},"title":"Registro de clientes","backgroundTitle":"","backgroundDescription":"","tags":[{"name":"Compra","type":"tag","displayName":"Compra"},{"name":"Compras en pagina de pruebas","type":"feature","displayName":"Compras en pagina de pruebas"}],"startTime":"2023-03-22T13:52:07.385374700-05:00[America/Bogota]","duration":16947,"testFailureCause":{"errorType":"org.openqa.selenium.NoSuchWindowException","message":"no such window: target window already closed\nfrom unknown error: web view not found\n  (Session info: chrome\u003d111.0.5563.65)\nBuild info: version: \u00273.141.59\u0027, revision: \u0027e82be7d358\u0027, time: \u00272018-11-14T08:17:03\u0027\nSystem info: host: \u0027LAPTOP-87LGHN0U\u0027, ip: \u0027192.168.0.5\u0027, os.name: \u0027Windows 11\u0027, os.arch: \u0027amd64\u0027, os.version: \u002710.0\u0027, java.version: \u002711.0.18\u0027\nDriver info: org.openqa.selenium.chrome.ChromeDriver\nCapabilities {acceptInsecureCerts: false, browserName: chrome, browserVersion: 111.0.5563.65, chrome: {chromedriverVersion: 111.0.5563.64 (c710e93d5b63..., userDataDir: C:\\Users\\ivan0\\AppData\\Loca...}, goog:chromeOptions: {debuggerAddress: localhost:55932}, javascriptEnabled: true, networkConnectionEnabled: false, pageLoadStrategy: normal, platform: WINDOWS, platformName: WINDOWS, proxy: Proxy(), setWindowRect: true, strictFileInteractability: false, timeouts: {implicit: 0, pageLoad: 300000, script: 30000}, unhandledPromptBehavior: ignore, webauthn:extension:credBlob: true, webauthn:extension:largeBlob: true, webauthn:extension:minPinLength: true, webauthn:extension:prf: true, webauthn:virtualAuthenticators: true}\nSession ID: 75a0a10f9f9f8880c527d66ca5a097ca","stackTrace":[{"classLoaderName":"app","declaringClass":"com.sofkau.tasks.Registrarse","methodName":"performAs","fileName":"Registrarse.java","lineNumber":44,"format":1},{"classLoaderName":"app","declaringClass":"com.sofkau.stepdefinitions.RegistroInicioSesionStepDefinitions","methodName":"llenaTodosLosCampos","fileName":"RegistroInicioSesionStepDefinitions.java","lineNumber":31,"format":1},{"classLoaderName":"app","declaringClass":"io.cucumber.java.Invoker","methodName":"invoke","fileName":"Invoker.java","lineNumber":27,"format":1},{"classLoaderName":"app","declaringClass":"io.cucumber.java.JavaStepDefinition","methodName":"execute","fileName":"JavaStepDefinition.java","lineNumber":27,"format":1},{"classLoaderName":"app","declaringClass":"io.cucumber.core.runner.PickleStepDefinitionMatch","methodName":"runStep","fileName":"PickleStepDefinitionMatch.java","lineNumber":63,"format":1},{"classLoaderName":"app","declaringClass":"io.cucumber.core.runner.TestStep","methodName":"executeStep","fileName":"TestStep.java","lineNumber":64,"format":1},{"classLoaderName":"app","declaringClass":"io.cucumber.core.runner.TestStep","methodName":"run","fileName":"TestStep.java","lineNumber":49,"format":1},{"classLoaderName":"app","declaringClass":"io.cucumber.core.runner.PickleStepTestStep","methodName":"run","fileName":"PickleStepTestStep.java","lineNumber":46,"format":1},{"classLoaderName":"app","declaringClass":"io.cucumber.core.runner.TestCase","methodName":"run","fileName":"TestCase.java","lineNumber":51,"format":1},{"classLoaderName":"app","declaringClass":"io.cucumber.core.runner.Runner","methodName":"runPickle","fileName":"Runner.java","lineNumber":67,"format":1},{"classLoaderName":"app","declaringClass":"io.cucumber.junit.FeatureRunner","methodName":"runChild","fileName":"FeatureRunner.java","lineNumber":83,"format":1},{"classLoaderName":"app","declaringClass":"io.cucumber.junit.FeatureRunner","methodName":"runChild","fileName":"FeatureRunner.java","lineNumber":24,"format":1},{"classLoaderName":"app","declaringClass":"io.cucumber.junit.CucumberSerenityRunner","methodName":"runChild","fileName":"CucumberSerenityRunner.java","lineNumber":227,"format":1},{"classLoaderName":"app","declaringClass":"io.cucumber.junit.CucumberSerenityRunner","methodName":"runChild","fileName":"CucumberSerenityRunner.java","lineNumber":54,"format":1},{"classLoaderName":"app","declaringClass":"worker.org.gradle.process.internal.worker.GradleWorkerMain","methodName":"run","fileName":"GradleWorkerMain.java","lineNumber":69,"format":1},{"classLoaderName":"app","declaringClass":"worker.org.gradle.process.internal.worker.GradleWorkerMain","methodName":"main","fileName":"GradleWorkerMain.java","lineNumber":74,"format":1}]},"testFailureClassname":"org.openqa.selenium.NoSuchWindowException","testFailureMessage":"no such window: target window already closed\nfrom unknown error: web view not found\n  (Session info: chrome\u003d111.0.5563.65)\nBuild info: version: \u00273.141.59\u0027, revision: \u0027e82be7d358\u0027, time: \u00272018-11-14T08:17:03\u0027\nSystem info: host: \u0027LAPTOP-87LGHN0U\u0027, ip: \u0027192.168.0.5\u0027, os.name: \u0027Windows 11\u0027, os.arch: \u0027amd64\u0027, os.version: \u002710.0\u0027, java.version: \u002711.0.18\u0027\nDriver info: org.openqa.selenium.chrome.ChromeDriver\nCapabilities {acceptInsecureCerts: false, browserName: chrome, browserVersion: 111.0.5563.65, chrome: {chromedriverVersion: 111.0.5563.64 (c710e93d5b63..., userDataDir: C:\\Users\\ivan0\\AppData\\Loca...}, goog:chromeOptions: {debuggerAddress: localhost:55932}, javascriptEnabled: true, networkConnectionEnabled: false, pageLoadStrategy: normal, platform: WINDOWS, platformName: WINDOWS, proxy: Proxy(), setWindowRect: true, strictFileInteractability: false, timeouts: {implicit: 0, pageLoad: 300000, script: 30000}, unhandledPromptBehavior: ignore, webauthn:extension:credBlob: true, webauthn:extension:largeBlob: true, webauthn:extension:minPinLength: true, webauthn:extension:prf: true, webauthn:virtualAuthenticators: true}\nSession ID: 75a0a10f9f9f8880c527d66ca5a097ca","testFailureSummary":"ERROR;org.openqa.selenium.NoSuchWindowException;no such window: target window already closed\nfrom unknown error: web view not found\n  (Session info: chrome\u003d111.0.5563.65)\nBuild info: version: \u00273.141.59\u0027, revision: \u0027e82be7d358\u0027, time: \u00272018-11-14T08:17:03\u0027\nSystem info: host: \u0027LAPTOP-87LGHN0U\u0027, ip: \u0027192.168.0.5\u0027, os.name: \u0027Windows 11\u0027, os.arch: \u0027amd64\u0027, os.version: \u002710.0\u0027, java.version: \u002711.0.18\u0027\nDriver info: org.openqa.selenium.chrome.ChromeDriver\nCapabilities {acceptInsecureCerts: false, browserName: chrome, browserVersion: 111.0.5563.65, chrome: {chromedriverVersion: 111.0.5563.64 (c710e93d5b63..., userDataDir: C:\\Users\\ivan0\\AppData\\Loca...}, goog:chromeOptions: {debuggerAddress: localhost:55932}, javascriptEnabled: true, networkConnectionEnabled: false, pageLoadStrategy: normal, platform: WINDOWS, platformName: WINDOWS, proxy: Proxy(), setWindowRect: true, strictFileInteractability: false, timeouts: {implicit: 0, pageLoad: 300000, script: 30000}, unhandledPromptBehavior: ignore, webauthn:extension:credBlob: true, webauthn:extension:largeBlob: true, webauthn:extension:minPinLength: true, webauthn:extension:prf: true, webauthn:virtualAuthenticators: true}\nSession ID: 75a0a10f9f9f8880c527d66ca5a097ca;Registrarse.java","projectKey":"","annotatedResult":"ERROR","sessionId":"75a0a10f9f9f8880c527d66ca5a097ca","driver":"chrome","isManualTestingUpToDate":false,"manual":false,"testSource":"Cucumber","actors":[{"name":"Juanes","can":["browse the web"]}],"result":"ERROR"}