{"name":"Registro de clientes","id":"compras-en-pagina-de-pruebas;registro-de-clientes","testSteps":[{"number":1,"description":"Dado que el usuario esta en la pagina de inicio","duration":21605,"startTime":"2023-03-22T12:28:12.444932400-05:00[America/Bogota]","screenshots":[{"screenshot":"aaf544c04a7a5fe063305187863c8eb7732f244ab623c6797a2b2b96f9cef38f.png","timeStamp":1679506114050}],"result":"SUCCESS","precondition":false,"level":0,"children":[{"number":2,"description":"Jose abrir pagina inicial","duration":8650,"startTime":"2023-03-22T12:28:25.376888300-05:00[America/Bogota]","screenshots":[{"screenshot":"ebfe05812cbfb1de22ad0a8b32c1052ee8438efdcae04a5a6f5b041fbb5e2917.png","timeStamp":1679506106612},{"screenshot":"aaf544c04a7a5fe063305187863c8eb7732f244ab623c6797a2b2b96f9cef38f.png","timeStamp":1679506114026}],"result":"SUCCESS","precondition":false,"level":1,"children":[{"number":3,"description":"Jose opens the Pagina inicial","duration":7349,"startTime":"2023-03-22T12:28:26.655064700-05:00[America/Bogota]","screenshots":[{"screenshot":"ebfe05812cbfb1de22ad0a8b32c1052ee8438efdcae04a5a6f5b041fbb5e2917.png","timeStamp":1679506107173},{"screenshot":"aaf544c04a7a5fe063305187863c8eb7732f244ab623c6797a2b2b96f9cef38f.png","timeStamp":1679506114004}],"result":"SUCCESS","precondition":false,"level":2}]}]},{"number":4,"description":"Cuando navega hasta la el formulario de registro","duration":3764,"startTime":"2023-03-22T12:28:34.053075800-05:00[America/Bogota]","screenshots":[{"screenshot":"ee4c6b6887103402030ef0f6d225ede76cf3e4adad375f8f0c900e3d0daa9c9a.png","timeStamp":1679506117817}],"result":"SUCCESS","precondition":false,"level":0,"children":[{"number":5,"description":"Jose navegar al registro","duration":2838,"startTime":"2023-03-22T12:28:34.969009400-05:00[America/Bogota]","screenshots":[{"screenshot":"ee4c6b6887103402030ef0f6d225ede76cf3e4adad375f8f0c900e3d0daa9c9a.png","timeStamp":1679506117807}],"result":"SUCCESS","precondition":false,"level":1,"children":[{"number":6,"description":"Jose clicks on Boton ir al registro","duration":2791,"startTime":"2023-03-22T12:28:35.008458100-05:00[America/Bogota]","screenshots":[{"screenshot":"ee4c6b6887103402030ef0f6d225ede76cf3e4adad375f8f0c900e3d0daa9c9a.png","timeStamp":1679506117800}],"result":"SUCCESS","precondition":false,"level":2}]}]},{"number":7,"description":"Y Llena todos los campos","duration":25461,"startTime":"2023-03-22T12:28:37.820316-05:00[America/Bogota]","screenshots":[{"screenshot":"540400461c9d388cb769bf9ffb25a6981032951db714c47bb384ee3ec812c051.png","timeStamp":1679506143281}],"result":"SUCCESS","precondition":false,"level":0,"children":[{"number":8,"description":"Jose iniciar registro","duration":5677,"startTime":"2023-03-22T12:28:37.848526600-05:00[America/Bogota]","screenshots":[{"screenshot":"b54bbb66957884fb9bbf9094b5808f499193e703045a7e367efc1998561cde89.png","timeStamp":1679506118268},{"screenshot":"765c6038f3667799e0645cb3368fe70009252fa101c3b72fb34c2f246f8268a2.png","timeStamp":1679506123526}],"result":"SUCCESS","precondition":false,"level":1,"children":[{"number":9,"description":"Jose enters \u0027deb.turner\u0027 into Campo nombre de usuario","duration":1532,"startTime":"2023-03-22T12:28:38.299259300-05:00[America/Bogota]","screenshots":[{"screenshot":"b54bbb66957884fb9bbf9094b5808f499193e703045a7e367efc1998561cde89.png","timeStamp":1679506118801},{"screenshot":"1378142655527c6050d789497044cb169dbf24a4d810d90a1837109000831d00.png","timeStamp":1679506119831}],"result":"SUCCESS","precondition":false,"level":2},{"number":10,"description":"Jose enters \u0027gail.little@yahoo.com\u0027 into Campo email","duration":1102,"startTime":"2023-03-22T12:28:39.834844100-05:00[America/Bogota]","screenshots":[{"screenshot":"1378142655527c6050d789497044cb169dbf24a4d810d90a1837109000831d00.png","timeStamp":1679506119850},{"screenshot":"37b4c9141763f730356c99c63f2e4ec210e8dfa05954861d748c94894af4a73b.png","timeStamp":1679506120936}],"result":"SUCCESS","precondition":false,"level":2},{"number":11,"description":"Jose clicks on ","duration":2578,"startTime":"2023-03-22T12:28:40.941211500-05:00[America/Bogota]","screenshots":[{"screenshot":"37b4c9141763f730356c99c63f2e4ec210e8dfa05954861d748c94894af4a73b.png","timeStamp":1679506120954},{"screenshot":"765c6038f3667799e0645cb3368fe70009252fa101c3b72fb34c2f246f8268a2.png","timeStamp":1679506123519}],"result":"SUCCESS","precondition":false,"level":2}]},{"number":12,"description":"Jose llenar registro","duration":19596,"startTime":"2023-03-22T12:28:43.675319300-05:00[America/Bogota]","screenshots":[{"screenshot":"cd72a81f8ce3609d97707b7d82e654149136a1873350cf4f7a60c74f6a1c0197.png","timeStamp":1679506124190},{"screenshot":"540400461c9d388cb769bf9ffb25a6981032951db714c47bb384ee3ec812c051.png","timeStamp":1679506143271}],"result":"SUCCESS","precondition":false,"level":1,"children":[{"number":13,"description":"Jose clicks on Selector de genero masculino","duration":671,"startTime":"2023-03-22T12:28:44.198023200-05:00[America/Bogota]","screenshots":[{"screenshot":"cd72a81f8ce3609d97707b7d82e654149136a1873350cf4f7a60c74f6a1c0197.png","timeStamp":1679506124211},{"screenshot":"0f15f74ed0cb19abd71a2eadd4db8fd7e4eb3139cf598120901b38e7845ec5c4.png","timeStamp":1679506124868}],"result":"SUCCESS","precondition":false,"level":2},{"number":14,"description":"Jose enters \u00274144435\u0027 into Campo de crear contrasena","duration":1290,"startTime":"2023-03-22T12:28:44.936465100-05:00[America/Bogota]","screenshots":[{"screenshot":"0f15f74ed0cb19abd71a2eadd4db8fd7e4eb3139cf598120901b38e7845ec5c4.png","timeStamp":1679506125353},{"screenshot":"77badc36ff38bc052a56e709034c7a3b382b8d6a4b660bbb8395b2aef01b7f47.png","timeStamp":1679506126226}],"result":"SUCCESS","precondition":false,"level":2},{"number":15,"description":"Jose selects 10 in Selector de dias","duration":1360,"startTime":"2023-03-22T12:28:46.325239100-05:00[America/Bogota]","screenshots":[{"screenshot":"20989861c73932775841f7cbd0c17e7c38bc7879c1e3ca23363dd6f89468eb24.png","timeStamp":1679506126853},{"screenshot":"01f8315baeab6e145e946e47557160942cbdc624867e4fd6cbabfa5f036b6740.png","timeStamp":1679506127685}],"result":"SUCCESS","precondition":false,"level":2},{"number":16,"description":"Jose selects 8 in Selector de meses","duration":742,"startTime":"2023-03-22T12:28:47.688344100-05:00[America/Bogota]","screenshots":[{"screenshot":"01f8315baeab6e145e946e47557160942cbdc624867e4fd6cbabfa5f036b6740.png","timeStamp":1679506127706},{"screenshot":"ddd9c13524cec2f8cfab0f5f788fbead965c97d1e577146b1980f40e3c74369a.png","timeStamp":1679506128430}],"result":"SUCCESS","precondition":false,"level":2},{"number":17,"description":"Jose selects 1987 in Selector de annos","duration":755,"startTime":"2023-03-22T12:28:48.433520300-05:00[America/Bogota]","screenshots":[{"screenshot":"ddd9c13524cec2f8cfab0f5f788fbead965c97d1e577146b1980f40e3c74369a.png","timeStamp":1679506128453},{"screenshot":"6d2bd7563ba6a61cfa6816ef3c762d62f1d3b068e577c932ea8521b49f4dfc8f.png","timeStamp":1679506129188}],"result":"SUCCESS","precondition":false,"level":2},{"number":18,"description":"Jose enters \u0027Angel\u0027 into Campo primer nombre","duration":1313,"startTime":"2023-03-22T12:28:49.271760200-05:00[America/Bogota]","screenshots":[{"screenshot":"fd0437dacf479e15a6684da6c01afba8427d9bda69d082c57aa7201e2ccc8db7.png","timeStamp":1679506129722},{"screenshot":"071848d184d89d6a38b20c50c0ce48e7fd7ca65bfd50ab79d9815d4c79814c03.png","timeStamp":1679506130585}],"result":"SUCCESS","precondition":false,"level":2},{"number":19,"description":"Jose enters \u0027Emmerich\u0027 into Campo apellido","duration":925,"startTime":"2023-03-22T12:28:50.587996300-05:00[America/Bogota]","screenshots":[{"screenshot":"071848d184d89d6a38b20c50c0ce48e7fd7ca65bfd50ab79d9815d4c79814c03.png","timeStamp":1679506130607},{"screenshot":"0ab2e54036217d92c3ebf3c39a0491be90ecc3174f73faebfbb00602a6f30ae4.png","timeStamp":1679506131512}],"result":"SUCCESS","precondition":false,"level":2},{"number":20,"description":"Jose enters \u0027Bartell-Blanda\u0027 into Campo nombre company","duration":914,"startTime":"2023-03-22T12:28:51.515577300-05:00[America/Bogota]","screenshots":[{"screenshot":"0ab2e54036217d92c3ebf3c39a0491be90ecc3174f73faebfbb00602a6f30ae4.png","timeStamp":1679506131530},{"screenshot":"d6e29044760702ffb62f39d7a67ce35a8d01e0025da96b2cc1e105810eec7285.png","timeStamp":1679506132430}],"result":"SUCCESS","precondition":false,"level":2},{"number":21,"description":"Jose enters \u002727176 Hillary Pine\u0027 into Campo direccion","duration":943,"startTime":"2023-03-22T12:28:52.433319200-05:00[America/Bogota]","screenshots":[{"screenshot":"d6e29044760702ffb62f39d7a67ce35a8d01e0025da96b2cc1e105810eec7285.png","timeStamp":1679506132446},{"screenshot":"074d57e69b79fcd0b6ca4a324dc0ec49a268b9ee22e3152e424b95fb0a77dab3.png","timeStamp":1679506133376}],"result":"SUCCESS","precondition":false,"level":2},{"number":22,"description":"Jose enters \u0027655 Maggio Plain\u0027 into Campo direccion2","duration":913,"startTime":"2023-03-22T12:28:53.379964700-05:00[America/Bogota]","screenshots":[{"screenshot":"074d57e69b79fcd0b6ca4a324dc0ec49a268b9ee22e3152e424b95fb0a77dab3.png","timeStamp":1679506133393},{"screenshot":"284d3ddc8dd565d77373224f5911329724a3776b56d36ed9b48d796667301b6e.png","timeStamp":1679506134291}],"result":"SUCCESS","precondition":false,"level":2},{"number":23,"description":"Jose selects Israel in Campo nombre pais","duration":761,"startTime":"2023-03-22T12:28:54.296055100-05:00[America/Bogota]","screenshots":[{"screenshot":"284d3ddc8dd565d77373224f5911329724a3776b56d36ed9b48d796667301b6e.png","timeStamp":1679506134308},{"screenshot":"d36a1f97e807752decaccf6588fb4dd508fda5e45b69b28403efb2a377b0efe5.png","timeStamp":1679506135057}],"result":"SUCCESS","precondition":false,"level":2},{"number":24,"description":"Jose enters \u0027Sri Lanka\u0027 into Campo nombre estado","duration":1448,"startTime":"2023-03-22T12:28:55.155060400-05:00[America/Bogota]","screenshots":[{"screenshot":"19f1bdb0704b8820f292c6bca6b1c03a9aebac2fbab73de34fad04a26fb758be.png","timeStamp":1679506135661},{"screenshot":"e58799201dfad1ec9ed403c6da2e6ece30fe86307cdef61ce450cd3a738730e5.png","timeStamp":1679506136603}],"result":"SUCCESS","precondition":false,"level":2},{"number":25,"description":"Jose enters \u0027Korea (Democratic People\u0027s Republic of)\u0027 into Campo nombre ciudad","duration":1063,"startTime":"2023-03-22T12:28:56.606464700-05:00[America/Bogota]","screenshots":[{"screenshot":"e58799201dfad1ec9ed403c6da2e6ece30fe86307cdef61ce450cd3a738730e5.png","timeStamp":1679506136616},{"screenshot":"d20f0845f924f4c366f3e67757a697a7c53e237bb17c433e98ea5c3a39f4fece.png","timeStamp":1679506137670}],"result":"SUCCESS","precondition":false,"level":2},{"number":26,"description":"Jose enters \u0027837471\u0027 into Campo codigo ZIP","duration":858,"startTime":"2023-03-22T12:28:57.673159900-05:00[America/Bogota]","screenshots":[{"screenshot":"d20f0845f924f4c366f3e67757a697a7c53e237bb17c433e98ea5c3a39f4fece.png","timeStamp":1679506137688},{"screenshot":"3ed35eb440ff7bef3faf1227fa183a34b601e99fbdaf3321142f9e05e761a5c5.png","timeStamp":1679506138531}],"result":"SUCCESS","precondition":false,"level":2},{"number":27,"description":"Jose enters \u00275819327557\u0027 into Campo numero de celular","duration":939,"startTime":"2023-03-22T12:28:58.534263-05:00[America/Bogota]","screenshots":[{"screenshot":"3ed35eb440ff7bef3faf1227fa183a34b601e99fbdaf3321142f9e05e761a5c5.png","timeStamp":1679506138546},{"screenshot":"c09162c83842ea43f06b47fc34b037df0a0fe1982478bcb3d4501361d43e1702.png","timeStamp":1679506139474}],"result":"SUCCESS","precondition":false,"level":2},{"number":28,"description":"Jose clicks on Boton crear cuenta","duration":3786,"startTime":"2023-03-22T12:28:59.477750500-05:00[America/Bogota]","screenshots":[{"screenshot":"c09162c83842ea43f06b47fc34b037df0a0fe1982478bcb3d4501361d43e1702.png","timeStamp":1679506139493},{"screenshot":"540400461c9d388cb769bf9ffb25a6981032951db714c47bb384ee3ec812c051.png","timeStamp":1679506143264}],"result":"SUCCESS","precondition":false,"level":2}]}]},{"number":29,"description":"Entonces el usuario debe ser redireccionado a la pagina principal","duration":2453,"startTime":"2023-03-22T12:29:03.285390400-05:00[America/Bogota]","screenshots":[{"screenshot":"e354942f16af0bbd8b4fa0181053a1e4ec218c236bf91e64ba7ade70f116ce5e.png","timeStamp":1679506145738}],"result":"SUCCESS","precondition":false,"level":0,"children":[{"number":30,"description":"Then mensaje registro should be \u0027ACCOUNT CREATED!\u0027","duration":1459,"startTime":"2023-03-22T12:29:03.540552300-05:00[America/Bogota]","screenshots":[{"screenshot":"8ec830be503dee0b52269aaa9045522b61830bfa5ee26150fa97b75c43c80c4b.png","timeStamp":1679506144262},{"screenshot":"8ec830be503dee0b52269aaa9045522b61830bfa5ee26150fa97b75c43c80c4b.png","timeStamp":1679506145000}],"result":"SUCCESS","precondition":false,"level":1}]}],"userStory":{"id":"compras-en-pagina-de-pruebas","storyName":"Compras en pagina de pruebas","path":"file:///C:/Users/nunez/Escritorio/Proyectos/Java/C1-2023-QA-Auto-DemoScreenPlay/ScreenPlayEjemploEs/src/test/resources/features/registrarse.feature","narrative":"  yo como usuario de la pagina automation exercise\n  quiero crear una cuenta e ingresar\n  para poder comprar productos en la página","type":"feature"},"featureTag":{"name":"Features/Compras en pagina de pruebas","type":"feature","displayName":"Features/Compras en pagina de pruebas"},"title":"Registro de clientes","backgroundTitle":"","backgroundDescription":"","tags":[{"name":"Registro","type":"tag","displayName":"Registro"},{"name":"Compras en pagina de pruebas","type":"feature","displayName":"Compras en pagina de pruebas"}],"startTime":"2023-03-22T12:28:12.072449100-05:00[America/Bogota]","duration":53672,"projectKey":"","sessionId":"e4e577c9d17b5c06c25a5e6306ad311a","driver":"chrome","isManualTestingUpToDate":false,"manual":false,"testSource":"Cucumber","actors":[{"name":"Jose","can":["browse the web"]}],"result":"SUCCESS"}